LICENSE
MANIFEST.in
README.md
pyproject.toml
src/c_loops.cc
src/c_loops.hh
src/cell.cc
src/cell.hh
src/cmd_line.cc
src/common.cc
src/common.hh
src/config.hh
src/container.cc
src/container.hh
src/container_prd.cc
src/container_prd.hh
src/pre_container.cc
src/pre_container.hh
src/rad_option.hh
src/unitcell.cc
src/unitcell.hh
src/v_base.cc
src/v_base.hh
src/v_base_wl.cc
src/v_compute.cc
src/v_compute.hh
src/voro++.cc
src/voro++.hh
src/wall.cc
src/wall.hh
src/worklist.hh
voropy/__init__.py
voropy/voroplusplus.cpp
voropy/voroplusplus.pyx
voropy.egg-info/PKG-INFO
voropy.egg-info/SOURCES.txt
voropy.egg-info/dependency_links.txt
voropy.egg-info/top_level.txt