Metadata-Version: 2.4
Name: voropy
Version: 1.0.0
Summary: Python interface to the Voro++ library
Author-email: Siyu Chen <sc2090@cam.ac.uk>
License-Expression: GPL-3.0-or-later
Requires-Python: >=3.7
License-File: LICENSE
Dynamic: license-file
